CHANGELOG.rst
MANIFEST.in
README.rst
setup.py
py3270/__init__.py
py3270/version.txt
py3270.egg-info/PKG-INFO
py3270.egg-info/SOURCES.txt
py3270.egg-info/dependency_links.txt
py3270.egg-info/not-zip-safe
py3270.egg-info/requires.txt
py3270.egg-info/top_level.txt