Metadata-Version: 1.1
Name: py3270
Version: 0.3.5
Summary: A Python interface to x3270, an IBM 3270 terminal emulator
Home-page: https://github.com/py3270/py3270
Author: Randy Syring
Author-email: randy.syring@level12.io
License: BSD
Platform: UNKNOWN
Classifier: Development Status :: 4 - Beta
Classifier: Intended Audience :: Developers
Classifier: License :: OSI Approved :: BSD License
Classifier: Operating System :: POSIX :: Linux
Classifier: Operating System :: Microsoft :: Windows
Classifier: Programming Language :: Python :: 2
Classifier: Programming Language :: Python :: 2.7
Classifier: Programming Language :: Python :: 3
Classifier: Programming Language :: Python :: 3.7
Classifier: Topic :: Terminals :: Terminal Emulators/X Terminals
